tt_umd/__init__.py
tt_umd/__init__.pyi
tt_umd/logging.py
tt_umd/logging.pyi
tt_umd/py.typed
tt_umd/tt_umd.cpython-39-x86_64-linux-gnu.so
tt_umd/wormhole.py
tt_umd/wormhole.pyi
tt_umd.libs/libhwloc-a765a097.so.15.2.0
tt_umd-0.9.1.dist-info/METADATA
tt_umd-0.9.1.dist-info/WHEEL
tt_umd-0.9.1.dist-info/RECORD
tt_umd-0.9.1.dist-info/licenses/LICENSE
tt_umd-0.9.1.dist-info/licenses/LICENSE_understanding.txt
tt_umd-0.9.1.dist-info/sboms/auditwheel.cdx.json
