Metadata-Version: 2.2
Name: tt-umd
Version: 0.9.1
Summary: User Mode Driver for tenstorrent
Author-Email: Tenstorrent <foundationsw-umd@tenstorrent.com>
License:                                  Apache License
Classifier: Development Status :: 4 - Beta
Classifier: Intended Audience :: Developers
Classifier: License :: OSI Approved :: Apache Software License
Classifier: Operating System :: POSIX :: Linux
Classifier: Programming Language :: Python :: 3
Classifier: Programming Language :: Python :: 3.9
Classifier: Programming Language :: Python :: 3.10
Classifier: Programming Language :: Python :: 3.11
Classifier: Programming Language :: Python :: 3.12
Classifier: Programming Language :: Python :: 3.13
Classifier: Programming Language :: C++
Classifier: Topic :: Software Development :: Libraries
Classifier: Topic :: System :: Hardware
Project-URL: Homepage, https://tenstorrent.com
Project-URL: Bug Reports, https://github.com/tenstorrent/tt-umd/issues
Project-URL: Source, https://github.com/tenstorrent/tt-umd
Project-URL: Documentation, https://github.com/tenstorrent/tt-umd/blob/main/README.md
